setup.py
yphtest/__init__.py
yphtest.egg-info/PKG-INFO
yphtest.egg-info/SOURCES.txt
yphtest.egg-info/dependency_links.txt
yphtest.egg-info/not-zip-safe
yphtest.egg-info/top_level.txt