Metadata-Version: 1.0
Name: yphtest
Version: 0.1
Summary: The yphtest joke in the world
Home-page: http://github.com/storborg/yphtest
Author: Flying Circus
Author-email: flyingcircus@example.com
License: MIT
Platform: UNKNOWN
